opentelemetry_instrumentor_dramatiq/__init__.py
opentelemetry_instrumentor_dramatiq/src/__init__.py
opentelemetry_instrumentor_dramatiq/src/package.py
opentelemetry_instrumentor_dramatiq/src/version.py
opentelemetry_instrumentor_dramatiq-0.1.2.dist-info/licenses/LICENSE
opentelemetry_instrumentor_dramatiq-0.1.2.dist-info/METADATA
opentelemetry_instrumentor_dramatiq-0.1.2.dist-info/WHEEL
opentelemetry_instrumentor_dramatiq-0.1.2.dist-info/top_level.txt
opentelemetry_instrumentor_dramatiq-0.1.2.dist-info/RECORD
