Metadata-Version: 2.4
Name: opentelemetry-instrumentor-dramatiq
Version: 0.1.2
Summary: An instrumentor for dramatiq library
Author-email: Sunil <shrest4647+pip@gmail.com>
License: MIT License
Project-URL: Homepage, https://github.com/Shrest4647/opentelemetry-instrumentor-dramatiq
Keywords: dramatiq,opentelemetry,instrumentation,tracing,telemetry
Classifier: License :: OSI Approved :: MIT License
Classifier: Programming Language :: Python
Classifier: Programming Language :: Python :: 3
Requires-Python: >=3.7
License-File: LICENSE
Requires-Dist: dramatiq>=1.2
Requires-Dist: opentelemetry-api>=1.11.0
Requires-Dist: opentelemetry-instrumentation>=0.31b0
Requires-Dist: opentelemetry-semantic-conventions
Provides-Extra: dev
Requires-Dist: pytest; extra == "dev"
Requires-Dist: pip-tools; extra == "dev"
Requires-Dist: bumpver; extra == "dev"
Requires-Dist: pika; extra == "dev"
Requires-Dist: redis; extra == "dev"
Dynamic: license-file
